<?xml version="1.0" encoding="UTF-8"?>
<LanguageData>
  
  <DR_BattleHammer.label>龙娘 战锤</DR_BattleHammer.label>
  <DR_BattleHammer.description>一柄内置了EMP发生器的战锤。当击中时会释放电击瘫痪机械装置。</DR_BattleHammer.description>

  <DR_BattleStaff_Beam.label>龙娘 光束法杖</DR_BattleStaff_Beam.label>
  <DR_BattleStaff_Beam.description>龙娘使用的法杖。能射出急冻光束。</DR_BattleStaff_Beam.description>

  <DR_BattleStaff_Flare.label>龙娘 火焰法杖</DR_BattleStaff_Flare.label>
  <DR_BattleStaff_Flare.description>龙娘使用的法杖。能射出火焰束。</DR_BattleStaff_Flare.description>
  
</LanguageData>